<root>
  <card>
    <id>JiaSiTe</id>
    <resource_id>mankind_jiasite</resource_id>
    <name>加斯特</name>
    <nickname>风暴战将</nickname>
    <attack>80</attack>
    <def>90</def>
    <mdef>30</mdef>
    <hit>0</hit>
    <flee>0</flee>
    <health>360</health>
    <race>0</race>
  </card>
  <card>
    <id>MengQi</id>
    <resource_id>mankind_mengqi</resource_id>
    <name>蒙奇</name>
    <nickname>铁血守卫</nickname>
    <attack>55</attack>
    <def>110</def>
    <mdef>35</mdef>
    <hit>0</hit>
    <flee>0</flee>
    <health>380</health>
    <race>0</race>
  </card>
  <card>
    <id>HuoBiDe</id>
    <resource_id>mankind_huobide</resource_id>
    <name>霍彼得</name>
    <nickname>鹰之猎魔者</nickname>
    <attack>70</attack>
    <def>80</def>
    <mdef>30</mdef>
    <hit>0</hit>
    <flee>0</flee>
    <health>380</health>
    <race>0</race>
  </card>
  <card>
    <id>HaiSe</id>
    <resource_id>mankind_haise</resource_id>
    <name>海瑟</name>
    <nickname>青春之舞</nickname>
    <attack>50</attack>
    <def>75</def>
    <mdef>45</mdef>
    <hit>0</hit>
    <flee>0</flee>
    <health>360</health>
    <race>0</race>
  </card>
  <card>
    <id>HaiNaWei</id>
    <resource_id>mankind_hainawei</resource_id>
    <name>海纳威</name>
    <nickname>神圣之心</nickname>
    <attack>65</attack>
    <def>100</def>
    <mdef>40</mdef>
    <hit>0</hit>
    <flee>0</flee>
    <health>370</health>
    <race>0</race>
  </card>
  <card>
    <id>FoLuoLin</id>
    <resource_id>mankind_foluolin</resource_id>
    <name>弗洛琳</name>
    <nickname>神之侍女</nickname>
    <attack>55</attack>
    <def>75</def>
    <mdef>40</mdef>
    <hit>0</hit>
    <flee>0</flee>
    <health>340</health>
    <race>0</race>
  </card>
  <card>
    <id>BiSiEr</id>
    <resource_id>undead_bisier</resource_id>
    <name>比斯尔</name>
    <nickname>堕落将军</nickname>
    <attack>80</attack>
    <def>95</def>
    <mdef>25</mdef>
    <hit>0</hit>
    <flee>0</flee>
    <health>370</health>
    <race>1</race>
  </card>
  <card>
    <id>PanNi</id>
    <resource_id>undead_panni</resource_id>
    <name>潘妮</name>
    <nickname>深渊之蛛</nickname>
    <attack>65</attack>
    <def>100</def>
    <mdef>35</mdef>
    <hit>0</hit>
    <flee>0</flee>
    <health>350</health>
    <race>1</race>
  </card>
  <card>
    <id>DiMeng</id>
    <resource_id>undead_dimeng</resource_id>
    <name>迪蒙</name>
    <nickname>摄魂师</nickname>
    <attack>55</attack>
    <def>80</def>
    <mdef>45</mdef>
    <hit>0</hit>
    <flee>0</flee>
    <health>335</health>
    <race>1</race>
  </card>
  <card>
    <id>PuLeiGe</id>
    <resource_id>undead_puleige</resource_id>
    <name>普雷格</name>
    <nickname>瘟疫之灵</nickname>
    <attack>60</attack>
    <def>90</def>
    <mdef>40</mdef>
    <hit>0</hit>
    <flee>0</flee>
    <health>330</health>
    <race>1</race>
  </card>
  <card>
    <id>JiaErMaZuo</id>
    <resource_id>undead_jiaermazuo</resource_id>
    <name>加尔玛佐</name>
    <nickname>恐惧之影</nickname>
    <attack>70</attack>
    <def>100</def>
    <mdef>35</mdef>
    <hit>0</hit>
    <flee>0</flee>
    <health>390</health>
    <race>1</race>
  </card>
  <card>
    <id>YinNuoRuiEr</id>
    <resource_id>heaven_yinnuoruier</resource_id>
    <name>因诺瑞尔</name>
    <nickname>命运炽天使</nickname>
    <attack>55</attack>
    <def>95</def>
    <mdef>35</mdef>
    <hit>0</hit>
    <flee>0</flee>
    <health>340</health>
    <race>2</race>
  </card>
  <card>
    <id>AiRuiSi</id>
    <resource_id>heaven_airuisi</resource_id>
    <name>艾瑞斯</name>
    <nickname>勇气炽天使</nickname>
    <attack>75</attack>
    <def>80</def>
    <mdef>40</mdef>
    <hit>0</hit>
    <flee>0</flee>
    <health>370</health>
    <race>2</race>
  </card>
  <card>
    <id>AoLiKeRuiSi</id>
    <resource_id>heaven_aolikeruisi</resource_id>
    <name>奥莉克瑞斯</name>
    <nickname>希望智天使</nickname>
    <attack>50</attack>
    <def>85</def>
    <mdef>55</mdef>
    <hit>0</hit>
    <flee>0</flee>
    <health>320</health>
    <race>2</race>
  </card>
  <card>
    <id>YouNuoRuiEr</id>
    <resource_id>heaven_younuoruier</resource_id>
    <name>尤诺瑞尔</name>
    <nickname>正义座天使</nickname>
    <attack>70</attack>
    <def>95</def>
    <mdef>35</mdef>
    <hit>0</hit>
    <flee>0</flee>
    <health>380</health>
    <race>2</race>
  </card>
  <card>
    <id>YiXiSi</id>
    <resource_id>heaven_yixisi</resource_id>
    <name>伊西斯</name>
    <nickname>守护主天使</nickname>
    <attack>55</attack>
    <def>120</def>
    <mdef>40</mdef>
    <hit>0</hit>
    <flee>0</flee>
    <health>400</health>
    <race>2</race>
  </card>
  <card>
    <id>NaLuKe</id>
    <resource_id>demon_naluke</resource_id>
    <name>纳鲁克</name>
    <nickname>傲慢</nickname>
    <attack>75</attack>
    <def>90</def>
    <mdef>35</mdef>
    <hit>0</hit>
    <flee>0</flee>
    <health>360</health>
    <race>3</race>
  </card>
  <card>
    <id>DeLaDiYa</id>
    <resource_id>demon_deladiya</resource_id>
    <name>德拉蒂亚</name>
    <nickname>贪婪</nickname>
    <attack>65</attack>
    <def>85</def>
    <mdef>40</mdef>
    <hit>0</hit>
    <flee>0</flee>
    <health>340</health>
    <race>3</race>
  </card>
  <card>
    <id>WoKeLieKe</id>
    <resource_id>demon_wokelieke</resource_id>
    <name>沃克列克</name>
    <nickname>懒惰</nickname>
    <attack>55</attack>
    <def>95</def>
    <mdef>35</mdef>
    <hit>0</hit>
    <flee>0</flee>
    <health>385</health>
    <race>3</race>
  </card>
  <card>
    <id>XiuErDun</id>
    <resource_id>demon_xiuerdun</resource_id>
    <name>修尔顿</name>
    <nickname>暴怒</nickname>
    <attack>80</attack>
    <def>85</def>
    <mdef>30</mdef>
    <hit>0</hit>
    <flee>0</flee>
    <health>355</health>
    <race>3</race>
  </card>
  <card>
    <id>MoTeDan</id>
    <resource_id>demon_motedan</resource_id>
    <name>莫特丹</name>
    <nickname>谎言</nickname>
    <attack>50</attack>
    <def>75</def>
    <mdef>45</mdef>
    <hit>0</hit>
    <flee>0</flee>
    <health>340</health>
    <race>3</race>
  </card>
  <card>
    <id>MaiYa</id>
    <resource_id>spirit_maiya</resource_id>
    <name>迈娅</name>
    <nickname>花之女皇</nickname>
    <attack>55</attack>
    <def>85</def>
    <mdef>45</mdef>
    <hit>0</hit>
    <flee>0</flee>
    <health>320</health>
    <race>4</race>
  </card>
  <card>
    <id>YiLan</id>
    <resource_id>spirit_yilan</resource_id>
    <name>伊兰</name>
    <nickname>和谐之音</nickname>
    <attack>60</attack>
    <def>90</def>
    <mdef>40</mdef>
    <hit>0</hit>
    <flee>0</flee>
    <health>360</health>
    <race>4</race>
  </card>
  <card>
    <id>WoDe</id>
    <resource_id>spirit_wode</resource_id>
    <name>沃德</name>
    <nickname>巨树之王</nickname>
    <attack>65</attack>
    <def>110</def>
    <mdef>30</mdef>
    <hit>0</hit>
    <flee>0</flee>
    <health>395</health>
    <race>4</race>
  </card>
  <card>
    <id>AiEr</id>
    <resource_id>spirit_aier</resource_id>
    <name>艾尔</name>
    <nickname>天空之眼</nickname>
    <attack>75</attack>
    <def>90</def>
    <mdef>50</mdef>
    <hit>0</hit>
    <flee>0</flee>
    <health>330</health>
    <race>4</race>
  </card>
  <card>
    <id>KaiWen</id>
    <resource_id>spirit_kaiwen</resource_id>
    <name>凯文</name>
    <nickname>自然之怒</nickname>
    <attack>65</attack>
    <def>95</def>
    <mdef>40</mdef>
    <hit>0</hit>
    <flee>0</flee>
    <health>350</health>
    <race>4</race>
  </card>
  <card>
    <id>KeLaTiSi</id>
    <resource_id>titan_kelatisi</resource_id>
    <name>克拉缇斯</name>
    <nickname>创世契约者</nickname>
    <attack>60</attack>
    <def>100</def>
    <mdef>50</mdef>
    <hit>0</hit>
    <flee>0</flee>
    <health>300</health>
    <race>5</race>
  </card>
  <card>
    <id>ATiMoSi</id>
    <resource_id>titan_atimosi</resource_id>
    <name>阿缇莫斯</name>
    <nickname>飓风烈焰契约</nickname>
    <attack>50</attack>
    <def>120</def>
    <mdef>100</mdef>
    <hit>0</hit>
    <flee>0</flee>
    <health>320</health>
    <race>5</race>
  </card>
  <card>
    <id>EKeErSi</id>
    <resource_id>titan_ekeersi</resource_id>
    <name>俄刻尔斯</name>
    <nickname>大地海洋契约</nickname>
    <attack>55</attack>
    <def>90</def>
    <mdef>115</mdef>
    <hit>0</hit>
    <flee>0</flee>
    <health>300</health>
    <race>5</race>
  </card>
  <card>
    <id>KeESi</id>
    <resource_id>titan_keesi</resource_id>
    <name>科俄斯</name>
    <nickname>智慧之巅</nickname>
    <attack>50</attack>
    <def>90</def>
    <mdef>150</mdef>
    <hit>0</hit>
    <flee>0</flee>
    <health>270</health>
    <race>5</race>
  </card>
  <card>
    <id>TiYa</id>
    <resource_id>titan_tiya</resource_id>
    <name>提亚</name>
    <nickname>复仇之神</nickname>
    <attack>45</attack>
    <def>120</def>
    <mdef>120</mdef>
    <hit>0</hit>
    <flee>0</flee>
    <health>300</health>
    <race>5</race>
  </card>
</root>